addition/__init__.py
addition/addition_by_five.py
divide/__init__.py
divide/divide_by_three.py
multiply/__init__.py
multiply/multiply_by_three.py
DPN_PACKAGE1-1.0.0.dist-info/LICENCE.txt
DPN_PACKAGE1-1.0.0.dist-info/METADATA
DPN_PACKAGE1-1.0.0.dist-info/WHEEL
DPN_PACKAGE1-1.0.0.dist-info/top_level.txt
DPN_PACKAGE1-1.0.0.dist-info/RECORD
