Metadata-Version: 2.1
Name: DPN_PACKAGE1
Version: 1.0.0
Summary: A simple Python package for addition, division, multiply by 3 and 5
Home-page: https://github.com/Dipayan26/DPN_PACKAGE1
Author: Dipayan Sarkar
Author-email: dipayansarkar26@gmail.com
Project-URL: repository, https://github.com/Dipayan26/DPN_PACKAGE1
Classifier: Programming Language :: Python :: 3
Classifier: License :: OSI Approved :: MIT License
Classifier: Operating System :: OS Independent
Requires-Python: >=3.6
License-File: LICENCE.txt
